pysondb/__init__.py
pysondb/cluster.py
pysondb/core.py
strip.pysondb-1.5.1.dist-info/LICENSE
strip.pysondb-1.5.1.dist-info/METADATA
strip.pysondb-1.5.1.dist-info/WHEEL
strip.pysondb-1.5.1.dist-info/top_level.txt
strip.pysondb-1.5.1.dist-info/RECORD
