Metadata-Version: 2.1
Name: strip.pysondb
Version: 1.5.1
Summary: A stripped-down version of pysondb.
Home-page: https://github.com/Adwaith-Rajesh/strip.pysondb
Author: Adwaith Rajesh
Author-email: adwaithrajesh3180@gmail.com
License: MIT
Platform: UNKNOWN
Classifier: License :: OSI Approved :: MIT License
Classifier: Programming Language :: Python :: 3
Classifier: Programming Language :: Python :: 3 :: Only
Classifier: Programming Language :: Python :: 3.6
Classifier: Programming Language :: Python :: 3.7
Classifier: Programming Language :: Python :: 3.8
Classifier: Programming Language :: Python :: 3.9
Requires-Python: >=3.6.1
